clovers_divine/__init__.py
clovers_divine/clovers.py
clovers_divine/config.py
clovers_divine/daily_fortune.py
clovers_divine/resource/copywriting.json
clovers_divine/resource/tarot.json
clovers_divine/tarot.py
clovers_divine-0.1.3.dist-info/LICENSE
clovers_divine-0.1.3.dist-info/METADATA
clovers_divine-0.1.3.dist-info/WHEEL
clovers_divine-0.1.3.dist-info/RECORD
